pyinstagraph/__init__.py
pyinstagraph-0.1.0.dist-info/LICENSE
pyinstagraph-0.1.0.dist-info/WHEEL
pyinstagraph-0.1.0.dist-info/METADATA
pyinstagraph-0.1.0.dist-info/RECORD
